py7z/__init__.py
py7z/main.py
py7z-0.2.dist-info/METADATA
py7z-0.2.dist-info/WHEEL
py7z-0.2.dist-info/top_level.txt
py7z-0.2.dist-info/RECORD
