Metadata-Version: 2.1
Name: py7z
Version: 0.2
Summary: Librería con funciones ya echas para ahorrarnos trabajo usando py7zr
Home-page: https://github.com/drug0drug
Author: Jean Diaz
Author-email: jeancodiaz148@gmail.com
License: MIT
Requires-Dist: py7zr
